<annotation>
	<folder>small</folder>
	<filename>312.jpg</filename>
	<path>D:\yinwu_program\cell_detection\crop_img\small\312.jpg</path>
	<source>
		<database>Unknown</database>
	</source>
	<size>
		<width>62</width>
		<height>62</height>
		<depth>1</depth>
	</size>
	<segmented>0</segmented>
	<object>
		<name>small</name>
		<pose>Unspecified</pose>
		<truncated>0</truncated>
		<difficult>0</difficult>
		<bndbox>
			<xmin>45</xmin>
			<ymin>22</ymin>
			<xmax>56</xmax>
			<ymax>32</ymax>
		</bndbox>
	</object>
	<object>
		<name>small</name>
		<pose>Unspecified</pose>
		<truncated>0</truncated>
		<difficult>0</difficult>
		<bndbox>
			<xmin>34</xmin>
			<ymin>39</ymin>
			<xmax>46</xmax>
			<ymax>49</ymax>
		</bndbox>
	</object>
</annotation>
